drawing/__init__.py
drawing/_version.py
drawing/drawing.py
nummulith_drawing-0.0.20.dist-info/LICENSE
nummulith_drawing-0.0.20.dist-info/METADATA
nummulith_drawing-0.0.20.dist-info/WHEEL
nummulith_drawing-0.0.20.dist-info/top_level.txt
nummulith_drawing-0.0.20.dist-info/RECORD
